moalerts/__init__.py
moalerts/alarms.csv
moalerts/core.py
moalerts/helpers.py
moalerts/notes.txt
moalerts/test.csv
mo_python-0.0.5.dist-info/LICENSE
mo_python-0.0.5.dist-info/METADATA
mo_python-0.0.5.dist-info/WHEEL
mo_python-0.0.5.dist-info/RECORD
